[{"code":"111105","desc":"Senador"},{"code":"111110","desc":"Deputado federal"},{"code":"111115","desc":"Deputado estadual e distrital"},{"code":"111120","desc":"Vereador"},{"code":"111205","desc":"Presidente da república"},{"code":"111210","desc":"Vice-presidente da república"},{"code":"111215","desc":"Ministro de estado"},{"code":"111305","desc":"Governador de estado"},{"code":"111310","desc":"Vice-governador de estado e do Distrito Federal"},{"code":"111405","desc":"Prefeito"},{"code":"111410","desc":"Vice-prefeito"},{"code":"114105","desc":"Dirigente geral de empresa e organizações"},{"code":"114205","desc":"Diretor administrativo e financeiro"},{"code":"114210","desc":"Diretor de recursos humanos"},{"code":"114215","desc":"Diretor comercial"},{"code":"114220","desc":"Diretor de operações de serviços"},{"code":"114305","desc":"Diretor de produção e operações"},{"code":"114315","desc":"Diretor de manutenção"},{"code":"114320","desc":"Diretor de suprimentos"},{"code":"114405","desc":"Diretor de tecnologia da informação"},{"code":"121005","desc":"Gerente administrativo"},{"code":"121010","desc":"Gerente de recursos humanos"},{"code":"121015","desc":"Gerente financeiro"},{"code":"121020","desc":"Gerente de riscos"},{"code":"121025","desc":"Gerente de contratos"},{"code":"122105","desc":"Gerente de produção e operações"},{"code":"122110","desc":"Gerente de manutenção"},{"code":"122115","desc":"Gerente de controle de qualidade"},{"code":"122205","desc":"Gerente de suprimentos"},{"code":"122210","desc":"Gerente de logística"},{"code":"123705","desc":"Gerente de tecnologia da informação"},{"code":"123710","desc":"Gerente de projetos de tecnologia"},{"code":"141010","desc":"Supervisor de loja"},{"code":"141205","desc":"Gerente de loja e supermercado"},{"code":"141305","desc":"Gerente de hotel"},{"code":"141405","desc":"Gerente de restaurante e afins"},{"code":"142105","desc":"Gerente de vendas"},{"code":"142110","desc":"Gerente comercial"},{"code":"142205","desc":"Gerente de marketing"},{"code":"142305","desc":"Gerente de projetos"},{"code":"142310","desc":"Gerente de qualidade"},{"code":"142310","desc":"Supervisor de qualidade"},{"code":"143005","desc":"Gerente de área e afins de saúde"},{"code":"191005","desc":"Diretor e gerente de empresa em geral"},{"code":"211105","desc":"Físico"},{"code":"211110","desc":"Astrônomo"},{"code":"212105","desc":"Matemático"},{"code":"212110","desc":"Estatístico"},{"code":"212115","desc":"Atuário"},{"code":"213105","desc":"Químico"},{"code":"213205","desc":"Engenheiro de materiais"},{"code":"213210","desc":"Físico"},{"code":"214105","desc":"Engenheiro civil"},{"code":"214110","desc":"Engenheiro de estruturas"},{"code":"214205","desc":"Engenheiro elétrico"},{"code":"214210","desc":"Engenheiro eletrônico"},{"code":"214215","desc":"Engenheiro de telecomunicações"},{"code":"214305","desc":"Engenheiro mecânico"},{"code":"214310","desc":"Engenheiro metalúrgico"},{"code":"214405","desc":"Engenheiro químico"},{"code":"214505","desc":"Engenheiro agrônomo"},{"code":"214605","desc":"Engenheiro de produção"},{"code":"214610","desc":"Engenheiro de segurança do trabalho"},{"code":"214615","desc":"Engenheiro de controle de qualidade"},{"code":"214705","desc":"Engenheiro de computação"},{"code":"214710","desc":"Engenheiro de software"},{"code":"215105","desc":"Analista de sistemas"},{"code":"215115","desc":"Programador de sistemas"},{"code":"215120","desc":"Administrador de banco de dados"},{"code":"215125","desc":"Analista de infraestrutura de TI"},{"code":"215130","desc":"Analista de suporte computacional"},{"code":"215205","desc":"Analista de negócios em TI"},{"code":"215215","desc":"Desenvolvedor de sistemas de informação"},{"code":"221105","desc":"Médico"},{"code":"221110","desc":"Médico clínico"},{"code":"221115","desc":"Médico de família e comunidade"},{"code":"221120","desc":"Médico cardiologista"},{"code":"221125","desc":"Médico cirurgião"},{"code":"221130","desc":"Médico neurologista"},{"code":"221135","desc":"Médico ortopedista"},{"code":"221140","desc":"Médico pediatra"},{"code":"221145","desc":"Médico ginecologista e obstetra"},{"code":"221205","desc":"Médico veterinário"},{"code":"222105","desc":"Enfermeiro"},{"code":"222115","desc":"Enfermeiro do trabalho"},{"code":"222120","desc":"Enfermeiro de UTI"},{"code":"222205","desc":"Farmacêutico"},{"code":"222215","desc":"Farmacêutico industrial"},{"code":"222305","desc":"Fisioterapeuta"},{"code":"222310","desc":"Terapeuta ocupacional"},{"code":"222405","desc":"Fonoaudiólogo"},{"code":"222505","desc":"Nutricionista"},{"code":"222605","desc":"Odontólogo"},{"code":"223205","desc":"Psicólogo"},{"code":"223210","desc":"Psicólogo clínico"},{"code":"223215","desc":"Psicólogo organizacional"},{"code":"224105","desc":"Assistente social"},{"code":"225105","desc":"Médico do trabalho"},{"code":"231105","desc":"Professor de educação infantil"},{"code":"231205","desc":"Professor de ensino fundamental"},{"code":"231310","desc":"Professor de ensino médio"},{"code":"232105","desc":"Professor universitário"},{"code":"239205","desc":"Orientador educacional"},{"code":"239415","desc":"Instrutor de treinamento e desenvolvimento profissional"},{"code":"241005","desc":"Advogado"},{"code":"241010","desc":"Advogado (direito do trabalho)"},{"code":"241015","desc":"Advogado (direito tributário)"},{"code":"241020","desc":"Advogado (direito empresarial)"},{"code":"241105","desc":"Consultor jurídico"},{"code":"242205","desc":"Promotor de justiça"},{"code":"242210","desc":"Procurador"},{"code":"243105","desc":"Juiz de direito"},{"code":"251105","desc":"Administrador"},{"code":"251110","desc":"Administrador de empresas"},{"code":"251115","desc":"Analista administrativo"},{"code":"251205","desc":"Administrador de sistemas"},{"code":"251305","desc":"Analista de organização e métodos"},{"code":"252105","desc":"Profissional de relações públicas"},{"code":"252205","desc":"Profissional de publicidade e propaganda"},{"code":"253105","desc":"Contador"},{"code":"253110","desc":"Auditor contábil"},{"code":"253115","desc":"Perito contábil"},{"code":"253120","desc":"Analista contábil"},{"code":"253505","desc":"Atuário"},{"code":"254105","desc":"Economista"},{"code":"261105","desc":"Jornalista"},{"code":"261115","desc":"Repórter de televisão"},{"code":"261205","desc":"Publicitário"},{"code":"261305","desc":"Redator de publicidade"},{"code":"261410","desc":"Escritor"},{"code":"261510","desc":"Intérprete"},{"code":"262110","desc":"Artista plástico"},{"code":"262205","desc":"Ator"},{"code":"262215","desc":"Diretor de cinema"},{"code":"262305","desc":"Músico"},{"code":"262310","desc":"Cantor"},{"code":"262405","desc":"Bailarino"},{"code":"263105","desc":"Ministro de culto religioso"},{"code":"311105","desc":"Técnico em geologia"},{"code":"311205","desc":"Técnico em mineração"},{"code":"311405","desc":"Técnico em química"},{"code":"311505","desc":"Técnico em petróleo"},{"code":"312105","desc":"Técnico de engenharia civil"},{"code":"312205","desc":"Técnico de engenharia elétrica"},{"code":"312305","desc":"Técnico de engenharia mecânica"},{"code":"312405","desc":"Técnico de controle de qualidade"},{"code":"313105","desc":"Técnico em eletricidade"},{"code":"313110","desc":"Técnico em eletrônica"},{"code":"313205","desc":"Técnico em telecomunicações"},{"code":"314105","desc":"Técnico em mecatrônica"},{"code":"317105","desc":"Programador de computador"},{"code":"317110","desc":"Analista de suporte de TI"},{"code":"317120","desc":"Técnico em manutenção de sistemas de informação"},{"code":"318005","desc":"Desenhista projetista (engenharia)"},{"code":"321105","desc":"Técnico de laboratório"},{"code":"321205","desc":"Técnico em saúde"},{"code":"322105","desc":"Técnico em enfermagem"},{"code":"322110","desc":"Técnico em enfermagem do trabalho"},{"code":"322205","desc":"Técnico em farmácia"},{"code":"322305","desc":"Técnico em fisioterapia"},{"code":"322405","desc":"Técnico em prótese dentária"},{"code":"322405","desc":"Técnico em higiene dental"},{"code":"322505","desc":"Técnico em radiologia"},{"code":"322510","desc":"Técnico em imagem e som"},{"code":"322905","desc":"Técnico em saúde bucal"},{"code":"325005","desc":"Técnico em medicina"},{"code":"331105","desc":"Professor de educação básica"},{"code":"332205","desc":"Instrutor de cursos livres"},{"code":"341105","desc":"Piloto de aviação"},{"code":"3421-05","desc":"Agente de informações turísticas"},{"code":"3421-10","desc":"Guia de turismo"},{"code":"3421-20","desc":"Tecnólogo em gestão de transportes"},{"code":"3421-25","desc":"Tecnólogo em logística de transporte"},{"code":"3421-30","desc":"Assistente de logística"},{"code":"3421-35","desc":"Analista de logística"},{"code":"3421-40","desc":"Coordenador de logística"},{"code":"3421-45","desc":"Supervisor de logística"},{"code":"342115","desc":"Técnico em transporte"},{"code":"351115","desc":"Técnico em contabilidade"},{"code":"351120","desc":"Agente contábil"},{"code":"351305","desc":"Técnico em administração"},{"code":"351310","desc":"Agente administrativo"},{"code":"351405","desc":"Técnico em finanças"},{"code":"351605","desc":"Técnico em comércio exterior"},{"code":"352205","desc":"Técnico em seguros"},{"code":"352305","desc":"Técnico em publicidade"},{"code":"354120","desc":"Assistente de recursos humanos"},{"code":"354125","desc":"Analista de recursos humanos"},{"code":"354130","desc":"Assistente pessoal (secretaria)"},{"code":"354135","desc":"Recrutador"},{"code":"354305","desc":"Auxiliar de pessoal"},{"code":"354405","desc":"Agente de compras"},{"code":"357105","desc":"Técnico em informática"},{"code":"357110","desc":"Técnico de suporte de TI"},{"code":"371105","desc":"Técnico em segurança do trabalho"},{"code":"371110","desc":"Inspetor de segurança do trabalho"},{"code":"374105","desc":"Técnico em segurança privada"},{"code":"377105","desc":"Técnico em biblioteconomia"},{"code":"391115","desc":"Analista de sistema de qualidade"},{"code":"410105","desc":"Assistente administrativo"},{"code":"410110","desc":"Auxiliar administrativo"},{"code":"4110-05","desc":"Assistente administrativo"},{"code":"4110-10","desc":"Auxiliar administrativo"},{"code":"411005","desc":"Escriturário"},{"code":"411010","desc":"Auxiliar de escritório"},{"code":"411020","desc":"Assistente de escritório"},{"code":"411025","desc":"Auxiliar de departamento pessoal"},{"code":"411030","desc":"Assistente de departamento pessoal"},{"code":"412105","desc":"Atendente de agência bancária"},{"code":"412110","desc":"Bancário"},{"code":"412115","desc":"Caixa bancário"},{"code":"421105","desc":"Caixa de banco"},{"code":"421110","desc":"Caixa de loja"},{"code":"421115","desc":"Caixa de supermercado"},{"code":"421205","desc":"Cobrador"},{"code":"4221-05","desc":"Recepcionista em geral"},{"code":"422105","desc":"Recepcionista"},{"code":"422110","desc":"Telefonista"},{"code":"422115","desc":"Operador de telemarketing"},{"code":"422120","desc":"Atendente de telemarketing"},{"code":"422205","desc":"Operador de central de atendimento"},{"code":"423105","desc":"Assistente de agência de correios"},{"code":"424105","desc":"Operador de cadastro"},{"code":"511105","desc":"Comissário de bordo"},{"code":"511205","desc":"Guia de turismo"},{"code":"511305","desc":"Agente de viagem"},{"code":"511505","desc":"Vigilante"},{"code":"511510","desc":"Segurança"},{"code":"511515","desc":"Porteiro"},{"code":"511520","desc":"Guarda"},{"code":"511525","desc":"Vigilante patrimonial"},{"code":"511605","desc":"Serviços de conservação e limpeza em geral"},{"code":"512105","desc":"Cozinheiro"},{"code":"512110","desc":"Auxiliar de cozinha"},{"code":"512115","desc":"Copeiro"},{"code":"512120","desc":"Garçom"},{"code":"512125","desc":"Barman"},{"code":"513105","desc":"Trabalhador doméstico nos serviços gerais"},{"code":"513110","desc":"Empregado doméstico"},{"code":"513205","desc":"Lavadeiro"},{"code":"513305","desc":"Passadeiro de roupas"},{"code":"5142-05","desc":"Faxineiro"},{"code":"514305","desc":"Faxineiro"},{"code":"514310","desc":"Auxiliar de serviços gerais"},{"code":"514315","desc":"Zelador"},{"code":"514320","desc":"Porteiro de edifício"},{"code":"515105","desc":"Motorista de carro de passeio"},{"code":"515110","desc":"Motorista de veículo pesado"},{"code":"515115","desc":"Motorista de caminhão"},{"code":"515120","desc":"Motorista de ônibus"},{"code":"515125","desc":"Motorista de táxi"},{"code":"515130","desc":"Motorista de ambulância"},{"code":"515135","desc":"Motorista carreteiro"},{"code":"515205","desc":"Motoboy"},{"code":"515210","desc":"Motofretista"},{"code":"516105","desc":"Tintureiro"},{"code":"516205","desc":"Cabeleireiro"},{"code":"516210","desc":"Manicure e pedicure"},{"code":"516215","desc":"Maquiador"},{"code":"516305","desc":"Assistente social e comunitário"},{"code":"516505","desc":"Técnico em estética"},{"code":"5174-05","desc":"Porteiro de edifício residencial"},{"code":"521105","desc":"Vendedor de comércio varejista"},{"code":"521110","desc":"Promotor de vendas"},{"code":"521115","desc":"Operador de caixa"},{"code":"521120","desc":"Repositor de mercadorias"},{"code":"521205","desc":"Demonstrador de produtos"},{"code":"522105","desc":"Vendedor interno"},{"code":"522110","desc":"Vendedor externo"},{"code":"522115","desc":"Vendedor porta a porta"},{"code":"523115","desc":"Atendente de farmácia"},{"code":"523120","desc":"Balconista"},{"code":"523125","desc":"Atendente de loja"},{"code":"524105","desc":"Supervisor de vendas"},{"code":"524205","desc":"Representante comercial"},{"code":"610005","desc":"Trabalhador rural"},{"code":"611005","desc":"Produtor agropecuário em geral"},{"code":"612005","desc":"Operador de máquinas agrícolas"},{"code":"710105","desc":"Minerador"},{"code":"711105","desc":"Operador de britador"},{"code":"712105","desc":"Técnico em edificações"},{"code":"715105","desc":"Carpinteiro"},{"code":"715110","desc":"Marceneiro"},{"code":"715115","desc":"Auxiliar de carpintaria"},{"code":"715210","desc":"Pedreiro"},{"code":"715215","desc":"Servente de obras"},{"code":"715220","desc":"Operário de construção civil"},{"code":"715405","desc":"Telhadeiro"},{"code":"715505","desc":"Pintor de obras"},{"code":"715510","desc":"Auxiliar de pintor"},{"code":"715605","desc":"Eletricista"},{"code":"715610","desc":"Instalador de sistemas elétricos"},{"code":"715705","desc":"Encanador"},{"code":"715710","desc":"Instalador de encanamento"},{"code":"715805","desc":"Serralheiro"},{"code":"715815","desc":"Soldador"},{"code":"717010","desc":"Gesseiro"},{"code":"717015","desc":"Azulejista"},{"code":"720105","desc":"Operador de torno"},{"code":"720110","desc":"Fresador"},{"code":"720115","desc":"Torneiro mecânico"},{"code":"721105","desc":"Mecânico de máquinas"},{"code":"721110","desc":"Mecânico de manutenção"},{"code":"721205","desc":"Mecânico de motor diesel"},{"code":"721305","desc":"Mecânico de automóveis"},{"code":"721310","desc":"Mecânico de caminhão"},{"code":"721315","desc":"Auxiliar de mecânico"},{"code":"721320","desc":"Mecânico de moto"},{"code":"721405","desc":"Borracheiro"},{"code":"721410","desc":"Balanceador e alinhador"},{"code":"722105","desc":"Ferramenteiro"},{"code":"722110","desc":"Matrizer"},{"code":"724105","desc":"Eletricista industrial"},{"code":"724110","desc":"Eletricista automotivo"},{"code":"724115","desc":"Auxiliar de eletricista"},{"code":"725105","desc":"Operador de eletrônica"},{"code":"730105","desc":"Operador de instalação química"},{"code":"731105","desc":"Ceramista"},{"code":"731305","desc":"Vidreiro"},{"code":"732115","desc":"Fundidor de metais"},{"code":"732205","desc":"Caldeireiro"},{"code":"733105","desc":"Funileiro"},{"code":"733110","desc":"Funileiro de automóveis"},{"code":"734105","desc":"Pintor industrial"},{"code":"735105","desc":"Operador de plásticos"},{"code":"740105","desc":"Técnico de manutenção elétrica e eletrônica"},{"code":"741105","desc":"Instalador de equipamentos elétricos"},{"code":"742105","desc":"Técnico de aparelhos eletrônicos"},{"code":"742210","desc":"Técnico em eletrônica"},{"code":"750105","desc":"Joalheiro"},{"code":"751005","desc":"Operador de costura industrial"},{"code":"752105","desc":"Sapateiro"},{"code":"753115","desc":"Costureiro"},{"code":"753120","desc":"Costureira"},{"code":"760105","desc":"Operador de gráfica"},{"code":"761105","desc":"Impressor"},{"code":"762105","desc":"Encadernador"},{"code":"763005","desc":"Operador de máquina de acabamento gráfico"},{"code":"770105","desc":"Padeiro"},{"code":"770110","desc":"Confeiteiro"},{"code":"770115","desc":"Auxiliar de padaria"},{"code":"771105","desc":"Carniceiro"},{"code":"771110","desc":"Açougueiro"},{"code":"772105","desc":"Processador de laticínios"},{"code":"772110","desc":"Queijeiro"},{"code":"780105","desc":"Estivador"},{"code":"781105","desc":"Operador de empilhadeira"},{"code":"781110","desc":"Movimentador de mercadorias"},{"code":"782105","desc":"Condutor de veículo de cargas"},{"code":"782110","desc":"Motorista de carga"},{"code":"7823-05","desc":"Motorista de carro de passeio"},{"code":"7823-10","desc":"Motorista de furgão ou veículo similar"},{"code":"7823-15","desc":"Motorista operacional de guincho"},{"code":"7823-20","desc":"Condutor de ambulância"},{"code":"7825-10","desc":"Motorista de caminhão (rotas regionais e internacionais)"},{"code":"783105","desc":"Operador de guindaste"},{"code":"784105","desc":"Auxiliar de logística"},{"code":"784110","desc":"Assistente de logística"},{"code":"784115","desc":"Operador de logística"},{"code":"7842-05","desc":"Alimentador de Linha de Produção"},{"code":"784205","desc":"Alimentador de linha de produção"},{"code":"811005","desc":"Operador de produção"},{"code":"812105","desc":"Operador de usina"},{"code":"813105","desc":"Operador de refinaria"},{"code":"820105","desc":"Operador de máquinas industriais"},{"code":"821105","desc":"Operador de torno CNC"},{"code":"821110","desc":"Operador de fresadora CNC"},{"code":"830105","desc":"Operador de instalação química"},{"code":"840105","desc":"Operador de máquinas de madeira"},{"code":"841105","desc":"Marceneiro industrial"},{"code":"848115","desc":"Operador de máquina de costura"},{"code":"862120","desc":"Operador de caldeira"},{"code":"863110","desc":"Operador de sistemas de refrigeração"},{"code":"863115","desc":"Técnico em refrigeração e ar condicionado"},{"code":"911105","desc":"Mecânico de manutenção de aeronaves"},{"code":"913105","desc":"Mecânico de manutenção de máquinas"},{"code":"913110","desc":"Lubrificador industrial"},{"code":"914105","desc":"Mecânico de manutenção de veículos"},{"code":"914110","desc":"Borracheiro"},{"code":"915105","desc":"Eletricista de manutenção industrial"},{"code":"915110","desc":"Eletricista de manutenção veicular"},{"code":"915205","desc":"Eletrônico de manutenção"},{"code":"919105","desc":"Trabalhador de manutenção geral"},{"code":"950105","desc":"Ajudante de eletricista"},{"code":"950110","desc":"Ajudante de encanador"},{"code":"950115","desc":"Ajudante geral"},{"code":"9919-05","desc":"Trabalhador de serviços gerais"},{"code":"992215","desc":"Pedreiro"},{"code":"993115","desc":"Auxiliar de serviços gerais"},{"code":"994225","desc":"Servente de pedreiro"}]